zai/__init__.py
zai/__main__.py
zai/ast_nodes.py
zai/env.py
zai/internal_error.py
zai/lexer.py
zai/objects.py
zai/parse.py
zai/tokens.py
zai/utils.py
zai/visitor.py
zai/vm.py
zai/stdlib/__init__.py
zai/stdlib/native_func.py
zai_pl-0.8.2.dist-info/LICENSE
zai_pl-0.8.2.dist-info/METADATA
zai_pl-0.8.2.dist-info/WHEEL
zai_pl-0.8.2.dist-info/entry_points.txt
zai_pl-0.8.2.dist-info/top_level.txt
zai_pl-0.8.2.dist-info/RECORD
