Metadata-Version: 2.1
Name: zai-pl
Version: 0.8.2
Summary: A small programming language written for learning purposes.
Home-page: https://github.com/sehnsucht13/zai-pl
Author: Yavor Konstantinov
Author-email: ykonstantinov1@gmail.com
License: GPLv3
Keywords: zai,programming-language,zai-pl
Platform: UNKNOWN
Classifier: Programming Language :: Python :: 3
Classifier: License :: OSI Approved :: GNU General Public License v3 (GPLv3)
Classifier: Operating System :: OS Independent
Classifier: Development Status :: 4 - Beta
Classifier: Programming Language :: Other
Classifier: Topic :: Software Development :: Interpreters
Requires-Python: >=3.6
